Metadata-Version: 2.1
Name: linetable
Version: 0.0.1
Summary: library to manage Python Locations Table
Home-page: 
Author: Alessandro Molina
Author-email: amol@turbogears.org
License: MIT
License-File: LICENSE
